[
    {
        "id": "4a88de8c-5c56-44e9-bd4d-3121b65e4f4a",
        "cpf": "61582271020",
        "nome": "Administrador",
        "telefone": "31988887777",
        "email": "admin@mail.com",
        "senha": "admin",
        "permissao": "admin",
        "endereco_interno": "N/A"
    },
    {
        "id": "cc71d150-675e-4780-9147-d5057156ff73",
        "cpf": "14402730066",
        "nome": "Portaria",
        "telefone": "31912123212",
        "email": "portaria@mail.com",
        "senha": "portaria",
        "permissao": "portaria",
        "endereco_interno": "N/A"
    },
    {
        "id": "78841cbb-ff23-4407-b7da-e4afcee07ac4",
        "cpf": "30245362053",
        "nome": "Julio Pedro da Paz",
        "telefone": "31982094203",
        "email": "juliop@mail.com",
        "senha": "juliop",
        "permissao": "user",
        "endereco_interno": "Bloco C - apto 401"
    },
    {
        "id": "dba1aacf-fb89-4fa5-b938-5b2441191444",
        "cpf": "63093790034",
        "nome": "Nicolas Nathan",
        "telefone": "31999704702",
        "email": "nicolas@mail.com",
        "senha": "nicolas",
        "permissao": "user",
        "endereco_interno": "Bloco A - apto 101"
    },
    {
        "id": "2ab4e884-9ad5-4b3a-b130-7121d127682a",
        "cpf": "27843918094",
        "nome": "Maria Alice Juliana",
        "telefone": "31993080793",
        "email": "mariaju@mail.com",
        "senha": "mariaju",
        "permissao": "user",
        "endereco_interno": "Bloco E - apto 101"
    }
]